hid.cpython-38-i386-linux-gnu.so
hidraw.cpython-38-i386-linux-gnu.so
hidapi.libs/libudev-18ae2bd6.so.1.6.3
hidapi.libs/libusb-1-ef7241d1.0.so.0.5.0
hidapi-0.15.0.dist-info/LICENSE-bsd.txt
hidapi-0.15.0.dist-info/LICENSE-gpl3.txt
hidapi-0.15.0.dist-info/LICENSE-orig.txt
hidapi-0.15.0.dist-info/LICENSE.txt
hidapi-0.15.0.dist-info/METADATA
hidapi-0.15.0.dist-info/WHEEL
hidapi-0.15.0.dist-info/top_level.txt
hidapi-0.15.0.dist-info/RECORD
hidapi-0.15.0.dist-info/sboms/auditwheel.cdx.json
