Metadata-Version: 2.1
Name: hidapi
Version: 0.15.0
Summary: A Cython interface to the hidapi from https://github.com/libusb/hidapi
Home-page: https://github.com/trezor/cython-hidapi
Author: Pavol Rusnak
Author-email: pavol@rusnak.io
Maintainer: Pavol Rusnak
Maintainer-email: pavol@rusnak.io
Classifier: Operating System :: MacOS :: MacOS X
Classifier: Operating System :: Microsoft :: Windows
Classifier: Operating System :: POSIX
Classifier: License :: OSI Approved :: BSD License
Classifier: License :: OSI Approved :: GNU General Public License v3 (GPLv3)
Classifier: Programming Language :: Python :: 3.10
Classifier: Programming Language :: Python :: 3.11
Classifier: Programming Language :: Python :: 3.12
Classifier: Programming Language :: Python :: 3.13
Classifier: Programming Language :: Python :: 3.14
License-File: LICENSE-bsd.txt
License-File: LICENSE-gpl3.txt
License-File: LICENSE-orig.txt
License-File: LICENSE.txt
